czmtestkit/__init__.py
czmtestkit/abaqus_modules/ADCB.py
czmtestkit/abaqus_modules/ADCB2.py
czmtestkit/abaqus_modules/ADCB2powerLaw.py
czmtestkit/abaqus_modules/ASLB.py
czmtestkit/abaqus_modules/ASLB2.py
czmtestkit/abaqus_modules/__init__.py
czmtestkit/abaqus_modules/postProc.py
czmtestkit/abaqus_modules/uelDef.py
czmtestkit/py_modules/__init__.py
czmtestkit/py_modules/analyticalMixedMode.py
czmtestkit/py_modules/readMsgFile.py
czmtestkit/py_modules/run_abq.py
czmtestkit/py_modules/simData.py
czmtestkit-1.1.0.dist-info/LICENSE
czmtestkit-1.1.0.dist-info/METADATA
czmtestkit-1.1.0.dist-info/WHEEL
czmtestkit-1.1.0.dist-info/top_level.txt
czmtestkit-1.1.0.dist-info/RECORD
