Metadata-Version: 2.1
Name: czmtestkit
Version: 1.1.0
Summary: Python + abaqus-python based package for testing Abaqus/CAE user element subrotines for cohesive zone models
Home-page: https://pypi.org/project/czmtestkit/
Download-URL: https://github.com/NMudunuru/CzmTestKit.git
Author: Nanditha Mudunuru, Miguel Bessa, Albert Turon
Author-email: nanditha.mudunuru@gmail.com
License: GNU GPL v3.0
Project-URL: Documentation, https://czmtestkit.readthedocs.io/en/latest/
Classifier: Programming Language :: Python
Classifier: Development Status :: 2 - Pre-Alpha
Requires-Python: >=3.9.1
License-File: LICENSE
Requires-Dist: numpy (>=1.22.1)
